PyOGRe/__init__.py
PyOGRe-0.1.0.dist-info/LICENSE.txt
PyOGRe-0.1.0.dist-info/METADATA
PyOGRe-0.1.0.dist-info/WHEEL
PyOGRe-0.1.0.dist-info/top_level.txt
PyOGRe-0.1.0.dist-info/RECORD
