Metadata-Version: 2.1
Name: PyOGRe
Version: 0.1.0
Summary: A Python Object-Oriented General Relativity Package
Home-page: https://baraksh.com/
Author: Barak Shoshany and Jared Wogan
Author-email: baraksh@gmail.com
License: MIT
Keywords: scientific-computing,differential-geometry,tensor,tensors,general-relativity
Platform: unix
Platform: linux
Platform: osx
Platform: cygwin
Platform: win32
Classifier: Programming Language :: Python :: 3
Classifier: Programming Language :: Python :: 3.8
Classifier: Programming Language :: Python :: 3.9
Classifier: Programming Language :: Python :: 3.10
Classifier: License :: OSI Approved :: MIT License
Classifier: Operating System :: OS Independent
Classifier: Topic :: Scientific/Engineering :: Mathematics
Classifier: Topic :: Scientific/Engineering :: Physics
Requires-Python: >=3.8
License-File: LICENSE.txt
Requires-Dist: IPython (>=7.10.0)
Requires-Dist: sympy (>=1.8)
